regression_testing_utils/__init__.py
regression_testing_utils/checker.py
regression_testing_utils/compare_csv_files.py
regression_testing_utils/compare_files.py
regression_testing_utils/compare_tab_files.py
regression_testing_utils/config_checker.py
regression_testing_utils/console_helper.py
regression_testing_utils/constants.py
regression_testing_utils/evaluator.py
regression_testing_utils/file_utils.py
regression_testing_utils/make_shell_scripts_and_aliases.py
regression_testing_utils/manager.py
regression_testing_utils/runner.py
regression_testing_utils/system_caller.py
regression_testing_utils/conf/config.yaml
regression_testing_utils-0.1.0.dist-info/AUTHORS.rst
regression_testing_utils-0.1.0.dist-info/METADATA
regression_testing_utils-0.1.0.dist-info/WHEEL
regression_testing_utils-0.1.0.dist-info/entry_points.txt
regression_testing_utils-0.1.0.dist-info/top_level.txt
regression_testing_utils-0.1.0.dist-info/RECORD
